birbtalk/__init__.py
birbtalk/birbtalk.py
birbtalk/components.py
birbtalk/langgpt.py
birbtalk/models.py
birbtalk/tools/__init__.py
birbtalk/tools/duckduckgo.py
birbtalk/tools/memory.py
birbtalk-0.1.9.dist-info/METADATA
birbtalk-0.1.9.dist-info/WHEEL
birbtalk-0.1.9.dist-info/licenses/LICENSE
birbtalk-0.1.9.dist-info/RECORD
