Metadata-Version: 2.4
Name: birbtalk
Version: 0.1.9
Summary: Modular Python library for working with LLM-based chat bots.
Project-URL: Homepage, https://github.com/alex-karev/birbtalk
Project-URL: Issues, https://github.com/alex-karev/birbtalk/issues
Author-email: Alex Karev <karev.as99@gmail.com>
License: MIT License
License-File: LICENSE
Classifier: Operating System :: OS Independent
Classifier: Programming Language :: Python :: 3
Requires-Python: >=3.10
Requires-Dist: haystack-ai==2.9.0
Requires-Dist: jsonschema==4.23.0
Requires-Dist: tiktoken==0.8.0
Provides-Extra: memory
Requires-Dist: fastembed-haystack==1.4.1; extra == 'memory'
Requires-Dist: onnxruntime==1.19.0; extra == 'memory'
Requires-Dist: qdrant-haystack==7.0.0; extra == 'memory'
Provides-Extra: search
Requires-Dist: duckduckgo-search==7.2.1; extra == 'search'
